CalcTool/__init__.py
CalcTool/main.py
CalcTool-0.1.4.7.dist-info/METADATA
CalcTool-0.1.4.7.dist-info/WHEEL
CalcTool-0.1.4.7.dist-info/top_level.txt
CalcTool-0.1.4.7.dist-info/RECORD
