Metadata-Version: 2.1
Name: CalcTool
Version: 0.1.4.7
Summary: Tools for calculations
Author: Zhu Chongjing
Author-email: zhuchongjing_pypi@163.com
Classifier: Programming Language :: Python :: 3
Classifier: License :: OSI Approved :: MIT License
Classifier: Operating System :: OS Independent
